{
	"owner":"Sean",
	"teamName":"🅱ig 🅱obs 🅱ussies",
	"roster":[
		{
			"firstName":"Justin",
			"lastName":"Herbert",
			"position":"QB",
			"team":"LAC",
			"addDate":"n/a",
			"draftInfo":{
				"draftRound":"4",
				"keep":"0"}},
		{
			"firstName":"Deebo",
			"lastName":"Samuel",
			"position":"WR",
			"team":"SF",
			"addDate":"n/a",
			"draftInfo":{
				"draftRound":"8",
				"keep":"1"}},
		{
			"firstName":"Stefon",
			"lastName":"Diggs",
			"position":"WR",
			"team":"BUF",
			"addDate":"n/a",
			"draftInfo":{
				"draftRound":"1",
				"keep":"0"}},
		{
			"firstName":"JK",
			"lastName":"Dobbins",
			"position":"RB",
			"team":"BAL",
			"addDate":"n/a",
			"draftInfo":{
				"draftRound":"13",
				"keep":"y1"}},
		{
			"firstName":"Aaron",
			"lastName":"Jones",
			"position":"RB",
			"team":"GB",
			"addDate":"n/a",
			"draftInfo":{
				"draftRound":"2",
				"keep":"0"}},
		{
			"firstName":"Darren",
			"lastName":"Waller",
			"position":"TE",
			"team":"LV",
			"addDate":"n/a",
			"draftInfo":{
				"draftRound":"3",
				"keep":"0"}},
		{
			"firstName":"Ezekiel",
			"lastName":"Eillott",
			"position":"RB",
			"team":"DAL",
			"addDate":"n/a",
			"draftInfo":{
				"draftRound":"3",
				"keep":"0"}},
		{
			"firstName":"DeAndre",
			"lastName":"Hopkins",
			"position":"WR",
			"team":"ARI",
			"addDate":"n/a",
			"draftInfo":{
				"draftRound":"10",
				"keep":"0"}},
		{
			"firstName":"Cordarrelle",
			"lastName":"Patterson",
			"position":"RB",
			"team":"ATL",
			"addDate":"n/a",
			"draftInfo":{
				"draftRound":"7",
				"keep":"0"}},
		{
			"firstName":"Greg",
			"lastName":"Dortch",
			"position":"WR",
			"team":"ARI",
			"addDate":"n/a",
			"draftInfo":{
				"draftRound":"--",
				"keep":"0"}},
        {
			"firstName":"Tyler",
			"lastName":"Allgeier",
			"position":"RB",
			"team":"ATL",
			"addDate":"12/01/22",
			"draftInfo":{
				"draftRound":"--",
				"keep":"0"}},
		{
			"firstName":"Greg",
			"lastName":"Dulcich",
			"position":"TE",
			"team":"DEN",
			"addDate":"n/a",
			"draftInfo":{
				"draftRound":"--",
				"keep":"0"}},
        {
			"firstName":"JuJU",
			"lastName":"Smith-Schuster",
			"position":"WR",
			"team":"PIT",
			"addDate":"n/a",
			"draftInfo":{
				"draftRound":"5",
				"keep":"0"}},
		{
			"firstName":"Younghoe",
			"lastName":"Koo",
			"position":"K",
			"team":"ATL",
			"addDate":"n/a",
			"draftInfo":{
				"draftRound":"13",
				"keep":"0"}},
		{
			"firstName":"Philadelphia",
			"lastName":"Eagles",
			"position":"DEF",
			"team":"PHI",
			"addDate":"n/a",
			"draftInfo":{
				"draftRound":"--",
				"keep":"0"}}
	]
}