{
	"owner":"Josh",
	"teamName":"FootBalls Deep",
	"roster":[
		{
			"firstName":"Lamar",
			"lastName":"Jackson",
			"position":"QB",
			"team":"BAL",
			"addDate":"n/a",
			"draftInfo":{
				"draftRound":"5",
				"keep":"y0"}},
		{
			"firstName":"Justin",
			"lastName":"Jefferson",
			"position":"WR",
			"team":"MIN",
			"addDate":"n/a",
			"draftInfo":{
				"draftRound":"2",
				"keep":"0"}},
		{
			"firstName":"Allen",
			"lastName":"Robinson II",
			"position":"WR",
			"team":"CHI",
			"addDate":"n/a",
			"draftInfo":{
				"draftRound":"3",
				"keep":"0"}},
		{
			"firstName":"Javonte",
			"lastName":"Williams",
			"position":"RB",
			"team":"DEN",
			"addDate":"n/a",
			"draftInfo":{
				"draftRound":"6",
				"keep":"0"}},
		{
			"firstName":"Jamaal",
			"lastName":"Williams",
			"position":"RB",
			"team":"DET",
			"addDate":"n/a",
			"draftInfo":{
				"draftRound":"10",
				"keep":"0"}},
		{
			"firstName":"Austin",
			"lastName":"Hooper",
			"position":"TE",
			"team":"CLE",
			"addDate":"n/a",
			"draftInfo":{
				"draftRound":"14",
				"keep":"0"}},
		{
			"firstName":"Dalvin",
			"lastName":"Cook",
			"position":"RB",
			"team":"MIN",
			"addDate":"n/a",
			"draftInfo":{
				"draftRound":"1",
				"keep":"0"}},
		{
			"firstName":"Devin",
			"lastName":"Singletary",
			"position":"RB",
			"team":"BUF",
			"addDate":"n/a",
			"draftInfo":{
				"draftRound":"11",
				"keep":"0"}},
		{
			"firstName":"Brandon",
			"lastName":"Aiyuk",
			"position":"WR",
			"team":"SF",
			"addDate":"n/a",
			"draftInfo":{
				"draftRound":"4",
				"keep":"0"}},
		{
			"firstName":"Logan",
			"lastName":"Thomas",
			"position":"TE",
			"team":"WAS",
			"addDate":"n/a",
			"draftInfo":{
				"draftRound":"7",
				"keep":"0"}},
		{
			"firstName":"Tyrell",
			"lastName":"Williams",
			"position":"WR",
			"team":"DET",
			"addDate":"n/a",
			"draftInfo":{
				"draftRound":"--",
				"keep":"0"}},
		{
			"firstName":"Matt",
			"lastName":"Ryan",
			"position":"QB",
			"team":"ATL",
			"addDate":"n/a",
			"draftInfo":{
				"draftRound":"12",
				"keep":"0"}},
		{
			"firstName":"Harrison",
			"lastName":"Butker",
			"position":"K",
			"team":"KC",
			"addDate":"n/a",
			"draftInfo":{
				"draftRound":"9",
				"keep":"0"}},
		{
			"firstName":"Pittsburgh",
			"lastName":"Steelers",
			"position":"DEF",
			"team":"PIT",
			"addDate":"n/a",
			"draftInfo":{
				"draftRound":"8",
				"keep":"0"}}
	]
}