{
	"owner":"Bobby",
	"teamName":"Double Cheeked Up",
	"roster":[
		{
			"firstName":"Josh",
			"lastName":"Allen",
			"position":"QB",
			"team":"BUF",
			"addDate":"n/a",
			"draftInfo":{
				"draftRound":"2",
				"keep":"0"}},
		{
			"firstName":"DJ",
			"lastName":"Moore",
			"position":"WR",
			"team":"CHI",
			"addDate":"n/a",
			"draftInfo":{
				"draftRound":"5",
				"keep":"0"}},
		{
			"firstName":"Quentin",
			"lastName":"Johnston",
			"position":"WR",
			"team":"LAC",
			"addDate":"09/10/25",
			"draftInfo":{
				"draftRound":"--",
				"keep":"0"}},
		{
			"firstName":"D'Andre",
			"lastName":"Swift",
			"position":"RB",
			"team":"CHI",
			"addDate":"n/a",
			"draftInfo":{
				"draftRound":"4",
				"keep":"0"}},
		{
			"firstName":"Kareem",
			"lastName":"Hunt",
			"position":"RB",
			"team":"KC",
			"addDate":"10/31/25",
			"draftInfo":{
				"draftRound":"--",
				"keep":"0"}},
		{
			"firstName":"Pat",
			"lastName":"Freiermuth",
			"position":"TE",
			"team":"PIT",
			"addDate":"11/14/25",
			"draftInfo":{
				"draftRound":"--",
				"keep":"0"}},
		{
			"firstName":"Bucky",
			"lastName":"Irving",
			"position":"RB",
			"team":"TB",
			"addDate":"n/a",
			"draftInfo":{
				"draftRound":"13",
				"keep":"1"}},
		{
			"firstName":"Rico",
			"lastName":"Dowdle",
			"position":"RB",
			"team":"CAR",
			"addDate":"10/03/25",
			"draftInfo":{
				"draftRound":"--",
				"keep":"0"}},
		{
			"firstName":"David",
			"lastName":"Montgomery",
			"position":"RB",
			"team":"DET",
			"addDate":"n/a",
			"draftInfo":{
				"draftRound":"6",
				"keep":"0"}},
		{
			"firstName":"Rhamondre",
			"lastName":"Stevenson",
			"position":"RB",
			"team":"NE",
			"addDate":"n/a",
			"draftInfo":{
				"draftRound":"9",
				"keep":"0"}},
		{
			"firstName":"Chris",
			"lastName":"Godwin Jr",
			"position":"WR",
			"team":"TB",
			"addDate":"n/a",
			"draftInfo":{
				"draftRound":"10",
				"keep":"0"}},
		{
			"firstName":"Troy",
			"lastName":"Franklin",
			"position":"WR",
			"team":"DEN",
			"addDate":"11/30/25",
			"draftInfo":{
				"draftRound":"--",
				"keep":"0"}},
		{
			"firstName":"Sam",
			"lastName":"LaPorta",
			"position":"TE",
			"team":"DET",
			"addDate":"n/a",
			"draftInfo":{
				"draftRound":"3",
				"keep":"0"}},
		{
			"firstName":"Drake",
			"lastName":"London",
			"position":"WR",
			"team":"ATL",
			"addDate":"n/a",
			"draftInfo":{
				"draftRound":"1",
				"keep":"0"}},
		{
			"firstName":"Harrison",
			"lastName":"Butker",
			"position":"K",
			"team":"KC",
			"addDate":"11/14/25",
			"draftInfo":{
				"draftRound":"--",
				"keep":"0"}},
		{
			"firstName":"Seattle",
			"lastName":"Seahawks",
			"position":"DEF",
			"team":"SEA",
			"addDate":"10/30/25",
			"draftInfo":{
				"draftRound":"--",
				"keep":"0"}}
	]
}